[
    {
        "central_user": "1439731007469412355",
        "adjacent_user": "1367531"
    },
    {
        "central_user": "1439731007469412355",
        "adjacent_user": "112477030"
    },
    {
        "central_user": "1439731007469412355",
        "adjacent_user": "85726335"
    },
    {
        "central_user": "1439731007469412355",
        "adjacent_user": "3096147528"
    },
    {
        "central_user": "1439731007469412355",
        "adjacent_user": "39344374"
    },
    {
        "central_user": "1439731007469412355",
        "adjacent_user": "629698642"
    },
    {
        "central_user": "1439731007469412355",
        "adjacent_user": "44196397"
    },
    {
        "central_user": "1439731007469412355",
        "adjacent_user": "803694179079458816"
    },
    {
        "central_user": "1439731007469412355",
        "adjacent_user": "30354991"
    },
    {
        "central_user": "1439731007469412355",
        "adjacent_user": "1349149096909668363"
    },
    {
        "central_user": "1439731007469412355",
        "adjacent_user": "1326229737551912960"
    },
    {
        "central_user": "1439731007469412355",
        "adjacent_user": "801203059359678464"
    },
    {
        "central_user": "1439731007469412355",
        "adjacent_user": "191871143"
    },
    {
        "central_user": "1439731007469412355",
        "adjacent_user": "3315264553"
    },
    {
        "central_user": "1439731007469412355",
        "adjacent_user": "890061634181373952"
    },
    {
        "central_user": "1439731007469412355",
        "adjacent_user": "1355721251180961792"
    },
    {
        "central_user": "1405719288862871554",
        "adjacent_user": "85726335"
    },
    {
        "central_user": "1405719288862871554",
        "adjacent_user": "939091"
    },
    {
        "central_user": "1405719288862871554",
        "adjacent_user": "32804484"
    },
    {
        "central_user": "1405719288862871554",
        "adjacent_user": "30354991"
    },
    {
        "central_user": "1405719288862871554",
        "adjacent_user": "1349149096909668363"
    },
    {
        "central_user": "1443033661545205760",
        "adjacent_user": "1242534200634478593"
    },
    {
        "central_user": "1443033661545205760",
        "adjacent_user": "1241075086565634048"
    },
    {
        "central_user": "1443033661545205760",
        "adjacent_user": "1619059471484948480"
    },
    {
        "central_user": "1443033661545205760",
        "adjacent_user": "1212728697431572480"
    },
    {
        "central_user": "1443033661545205760",
        "adjacent_user": "240454812"
    },
    {
        "central_user": "1443033661545205760",
        "adjacent_user": "44196397"
    },
    {
        "central_user": "1443033661545205760",
        "adjacent_user": "828454426088050688"
    },
    {
        "central_user": "16585184",
        "adjacent_user": "1349149096909668363"
    },
    {
        "central_user": "16585184",
        "adjacent_user": "1326229737551912960"
    },
    {
        "central_user": "16585184",
        "adjacent_user": "3315264553"
    },
    {
        "central_user": "16585184",
        "adjacent_user": "890061634181373952"
    },
    {
        "central_user": "16585184",
        "adjacent_user": "1355721251180961792"
    },
    {
        "central_user": "16585184",
        "adjacent_user": "1367531"
    },
    {
        "central_user": "16585184",
        "adjacent_user": "1323730225067339784"
    },
    {
        "central_user": "16585184",
        "adjacent_user": "55329156"
    },
    {
        "central_user": "16585184",
        "adjacent_user": "130003441"
    },
    {
        "central_user": "16585184",
        "adjacent_user": "1082197856"
    },
    {
        "central_user": "16585184",
        "adjacent_user": "4239551"
    },
    {
        "central_user": "16585184",
        "adjacent_user": "44196397"
    },
    {
        "central_user": "16585184",
        "adjacent_user": "939091"
    },
    {
        "central_user": "16585184",
        "adjacent_user": "46302096"
    },
    {
        "central_user": "938478035484811264",
        "adjacent_user": "1586889837386276864"
    },
    {
        "central_user": "938478035484811264",
        "adjacent_user": "1594006318326730753"
    },
    {
        "central_user": "938478035484811264",
        "adjacent_user": "803694179079458816"
    },
    {
        "central_user": "938478035484811264",
        "adjacent_user": "811757810841255936"
    },
    {
        "central_user": "938478035484811264",
        "adjacent_user": "1658544339574743044"
    },
    {
        "central_user": "938478035484811264",
        "adjacent_user": "1226916043278442496"
    },
    {
        "central_user": "938478035484811264",
        "adjacent_user": "1421125270099087360"
    },
    {
        "central_user": "938478035484811264",
        "adjacent_user": "1586012373290205185"
    },
    {
        "central_user": "938478035484811264",
        "adjacent_user": "19301471"
    },
    {
        "central_user": "1621518536496812034",
        "adjacent_user": "69156861"
    },
    {
        "central_user": "1621518536496812034",
        "adjacent_user": "191871143"
    },
    {
        "central_user": "1621518536496812034",
        "adjacent_user": "39844876"
    },
    {
        "central_user": "1621518536496812034",
        "adjacent_user": "815966620300480514"
    },
    {
        "central_user": "1621518536496812034",
        "adjacent_user": "1619059471484948480"
    },
    {
        "central_user": "2206300538",
        "adjacent_user": "1593635660681957399"
    },
    {
        "central_user": "2206300538",
        "adjacent_user": "4018888580"
    },
    {
        "central_user": "2206300538",
        "adjacent_user": "279390084"
    },
    {
        "central_user": "2206300538",
        "adjacent_user": "44196397"
    },
    {
        "central_user": "2206300538",
        "adjacent_user": "256154569"
    },
    {
        "central_user": "2206300538",
        "adjacent_user": "1686901686185721857"
    },
    {
        "central_user": "2206300538",
        "adjacent_user": "818893114979061761"
    },
    {
        "central_user": "2206300538",
        "adjacent_user": "3315264553"
    },
    {
        "central_user": "2206300538",
        "adjacent_user": "1221462414744596483"
    },
    {
        "central_user": "53842814",
        "adjacent_user": "11134252"
    },
    {
        "central_user": "53842814",
        "adjacent_user": "1591834567207522305"
    },
    {
        "central_user": "53842814",
        "adjacent_user": "1108472017144201216"
    },
    {
        "central_user": "53842814",
        "adjacent_user": "1082197856"
    },
    {
        "central_user": "89421672",
        "adjacent_user": "1350150750966603777"
    },
    {
        "central_user": "89421672",
        "adjacent_user": "1323730225067339784"
    },
    {
        "central_user": "89421672",
        "adjacent_user": "14499829"
    },
    {
        "central_user": "89421672",
        "adjacent_user": "178978113"
    },
    {
        "central_user": "89421672",
        "adjacent_user": "1333171793201225728"
    },
    {
        "central_user": "89421672",
        "adjacent_user": "1496321911218917383"
    },
    {
        "central_user": "89421672",
        "adjacent_user": "1967216306"
    },
    {
        "central_user": "89421672",
        "adjacent_user": "1349149096909668363"
    },
    {
        "central_user": "89421672",
        "adjacent_user": "9624742"
    },
    {
        "central_user": "1044231098006425601",
        "adjacent_user": "39344374"
    },
    {
        "central_user": "1044231098006425601",
        "adjacent_user": "880412538625810432"
    },
    {
        "central_user": "1044231098006425601",
        "adjacent_user": "3066800573"
    },
    {
        "central_user": "1044231098006425601",
        "adjacent_user": "44196397"
    },
    {
        "central_user": "1044231098006425601",
        "adjacent_user": "240454812"
    },
    {
        "central_user": "1044231098006425601",
        "adjacent_user": "9624742"
    },
    {
        "central_user": "1044231098006425601",
        "adjacent_user": "1355721251180961792"
    },
    {
        "central_user": "1044231098006425601",
        "adjacent_user": "1242534200634478593"
    },
    {
        "central_user": "1577285647383121921",
        "adjacent_user": "803694179079458816"
    },
    {
        "central_user": "1577285647383121921",
        "adjacent_user": "30354991"
    },
    {
        "central_user": "1577285647383121921",
        "adjacent_user": "3315264553"
    },
    {
        "central_user": "1577285647383121921",
        "adjacent_user": "44196397"
    },
    {
        "central_user": "1630461606193930240",
        "adjacent_user": "1120077618076880897"
    },
    {
        "central_user": "1630461606193930240",
        "adjacent_user": "267695291"
    },
    {
        "central_user": "1630461606193930240",
        "adjacent_user": "89421672"
    },
    {
        "central_user": "1630461606193930240",
        "adjacent_user": "3026990185"
    },
    {
        "central_user": "1630461606193930240",
        "adjacent_user": "1683440309768708096"
    },
    {
        "central_user": "1630461606193930240",
        "adjacent_user": "1255201907867439104"
    },
    {
        "central_user": "1630461606193930240",
        "adjacent_user": "1260881050005315586"
    },
    {
        "central_user": "1630461606193930240",
        "adjacent_user": "1763352305309757440"
    },
    {
        "central_user": "1630461606193930240",
        "adjacent_user": "1574690362626494466"
    },
    {
        "central_user": "1630461606193930240",
        "adjacent_user": "1448120798934224899"
    },
    {
        "central_user": "1630461606193930240",
        "adjacent_user": "1619059471484948480"
    },
    {
        "central_user": "1586889837386276864",
        "adjacent_user": "1586012373290205185"
    },
    {
        "central_user": "1586889837386276864",
        "adjacent_user": "1393763457539977216"
    },
    {
        "central_user": "1586889837386276864",
        "adjacent_user": "19301471"
    },
    {
        "central_user": "1586889837386276864",
        "adjacent_user": "938478035484811264"
    },
    {
        "central_user": "1586889837386276864",
        "adjacent_user": "1676993370533634049"
    },
    {
        "central_user": "1586889837386276864",
        "adjacent_user": "1594006318326730753"
    },
    {
        "central_user": "1586889837386276864",
        "adjacent_user": "803694179079458816"
    },
    {
        "central_user": "1586889837386276864",
        "adjacent_user": "811757810841255936"
    },
    {
        "central_user": "1586889837386276864",
        "adjacent_user": "30354991"
    },
    {
        "central_user": "1586889837386276864",
        "adjacent_user": "1658544339574743044"
    },
    {
        "central_user": "1586889837386276864",
        "adjacent_user": "1226916043278442496"
    },
    {
        "central_user": "1586889837386276864",
        "adjacent_user": "1513958941536886787"
    },
    {
        "central_user": "1586889837386276864",
        "adjacent_user": "830465860825292800"
    },
    {
        "central_user": "1586889837386276864",
        "adjacent_user": "1421125270099087360"
    },
    {
        "central_user": "1586889837386276864",
        "adjacent_user": "1685762052252368896"
    },
    {
        "central_user": "1544939293319188480",
        "adjacent_user": "3910925474"
    },
    {
        "central_user": "1544939293319188480",
        "adjacent_user": "1735221284219310080"
    },
    {
        "central_user": "1544939293319188480",
        "adjacent_user": "1569434143540531200"
    },
    {
        "central_user": "1544939293319188480",
        "adjacent_user": "19140447"
    },
    {
        "central_user": "1544939293319188480",
        "adjacent_user": "1235110990347268096"
    },
    {
        "central_user": "1544939293319188480",
        "adjacent_user": "242984494"
    },
    {
        "central_user": "1594006318326730753",
        "adjacent_user": "803694179079458816"
    },
    {
        "central_user": "1594006318326730753",
        "adjacent_user": "811757810841255936"
    },
    {
        "central_user": "1594006318326730753",
        "adjacent_user": "1658544339574743044"
    },
    {
        "central_user": "1594006318326730753",
        "adjacent_user": "1226916043278442496"
    },
    {
        "central_user": "1594006318326730753",
        "adjacent_user": "1421125270099087360"
    },
    {
        "central_user": "1594006318326730753",
        "adjacent_user": "1586012373290205185"
    },
    {
        "central_user": "1594006318326730753",
        "adjacent_user": "1586889837386276864"
    },
    {
        "central_user": "1594006318326730753",
        "adjacent_user": "938478035484811264"
    },
    {
        "central_user": "1594006318326730753",
        "adjacent_user": "19301471"
    },
    {
        "central_user": "1500593146190729217",
        "adjacent_user": "3315264553"
    },
    {
        "central_user": "1500593146190729217",
        "adjacent_user": "1519657253799817218"
    },
    {
        "central_user": "1500593146190729217",
        "adjacent_user": "11134252"
    },
    {
        "central_user": "1500593146190729217",
        "adjacent_user": "1686901686185721857"
    },
    {
        "central_user": "1500593146190729217",
        "adjacent_user": "1108472017144201216"
    },
    {
        "central_user": "1337965898976485376",
        "adjacent_user": "30354991"
    },
    {
        "central_user": "1337965898976485376",
        "adjacent_user": "818893114979061761"
    },
    {
        "central_user": "1337965898976485376",
        "adjacent_user": "1323730225067339784"
    },
    {
        "central_user": "1337965898976485376",
        "adjacent_user": "69156861"
    },
    {
        "central_user": "1337965898976485376",
        "adjacent_user": "803694179079458816"
    },
    {
        "central_user": "118838969",
        "adjacent_user": "20784367"
    },
    {
        "central_user": "118838969",
        "adjacent_user": "55964567"
    },
    {
        "central_user": "118838969",
        "adjacent_user": "39030654"
    },
    {
        "central_user": "118838969",
        "adjacent_user": "880412538625810432"
    },
    {
        "central_user": "1303797208312094722",
        "adjacent_user": "1367531"
    },
    {
        "central_user": "1303797208312094722",
        "adjacent_user": "1082197856"
    },
    {
        "central_user": "1303797208312094722",
        "adjacent_user": "15843059"
    },
    {
        "central_user": "1303797208312094722",
        "adjacent_user": "537709549"
    },
    {
        "central_user": "1303797208312094722",
        "adjacent_user": "240454812"
    },
    {
        "central_user": "1303797208312094722",
        "adjacent_user": "44196397"
    },
    {
        "central_user": "1303797208312094722",
        "adjacent_user": "611986351"
    },
    {
        "central_user": "1303797208312094722",
        "adjacent_user": "191871143"
    },
    {
        "central_user": "1303797208312094722",
        "adjacent_user": "1242534200634478593"
    },
    {
        "central_user": "1164727944",
        "adjacent_user": "75343905"
    },
    {
        "central_user": "1164727944",
        "adjacent_user": "811229675758505984"
    },
    {
        "central_user": "1164727944",
        "adjacent_user": "1117210361592205312"
    },
    {
        "central_user": "1164727944",
        "adjacent_user": "351120282"
    },
    {
        "central_user": "1164727944",
        "adjacent_user": "1429400366819512323"
    },
    {
        "central_user": "1164727944",
        "adjacent_user": "44196397"
    },
    {
        "central_user": "1164727944",
        "adjacent_user": "91416107"
    },
    {
        "central_user": "1164727944",
        "adjacent_user": "1133510366422392833"
    },
    {
        "central_user": "1164727944",
        "adjacent_user": "629698642"
    },
    {
        "central_user": "1164727944",
        "adjacent_user": "1326229737551912960"
    },
    {
        "central_user": "1164727944",
        "adjacent_user": "801203059359678464"
    },
    {
        "central_user": "1164727944",
        "adjacent_user": "116579971"
    },
    {
        "central_user": "1164727944",
        "adjacent_user": "1222773302441148416"
    },
    {
        "central_user": "1164727944",
        "adjacent_user": "14159148"
    },
    {
        "central_user": "770917402196402176",
        "adjacent_user": "1222773302441148416"
    },
    {
        "central_user": "770917402196402176",
        "adjacent_user": "42604302"
    },
    {
        "central_user": "770917402196402176",
        "adjacent_user": "244917756"
    },
    {
        "central_user": "770917402196402176",
        "adjacent_user": "811229675758505984"
    },
    {
        "central_user": "770917402196402176",
        "adjacent_user": "69181624"
    },
    {
        "central_user": "770917402196402176",
        "adjacent_user": "848279118"
    },
    {
        "central_user": "1033415106531655685",
        "adjacent_user": "803694179079458816"
    },
    {
        "central_user": "1033415106531655685",
        "adjacent_user": "30354991"
    },
    {
        "central_user": "1033415106531655685",
        "adjacent_user": "1349149096909668363"
    },
    {
        "central_user": "1033415106531655685",
        "adjacent_user": "1323730225067339784"
    },
    {
        "central_user": "1033415106531655685",
        "adjacent_user": "939091"
    },
    {
        "central_user": "795879421",
        "adjacent_user": "91416107"
    },
    {
        "central_user": "795879421",
        "adjacent_user": "81371986"
    },
    {
        "central_user": "795879421",
        "adjacent_user": "629698642"
    },
    {
        "central_user": "795879421",
        "adjacent_user": "191871143"
    },
    {
        "central_user": "1226916043278442496",
        "adjacent_user": "1421125270099087360"
    },
    {
        "central_user": "1226916043278442496",
        "adjacent_user": "1685762052252368896"
    },
    {
        "central_user": "1226916043278442496",
        "adjacent_user": "1586012373290205185"
    },
    {
        "central_user": "1226916043278442496",
        "adjacent_user": "1393763457539977216"
    },
    {
        "central_user": "1226916043278442496",
        "adjacent_user": "19301471"
    },
    {
        "central_user": "1226916043278442496",
        "adjacent_user": "1586889837386276864"
    },
    {
        "central_user": "1226916043278442496",
        "adjacent_user": "938478035484811264"
    },
    {
        "central_user": "1226916043278442496",
        "adjacent_user": "1676993370533634049"
    },
    {
        "central_user": "1226916043278442496",
        "adjacent_user": "1594006318326730753"
    },
    {
        "central_user": "1226916043278442496",
        "adjacent_user": "803694179079458816"
    },
    {
        "central_user": "1226916043278442496",
        "adjacent_user": "811757810841255936"
    },
    {
        "central_user": "1226916043278442496",
        "adjacent_user": "1658544339574743044"
    },
    {
        "central_user": "1226916043278442496",
        "adjacent_user": "1513958941536886787"
    },
    {
        "central_user": "1226916043278442496",
        "adjacent_user": "830465860825292800"
    },
    {
        "central_user": "366785595",
        "adjacent_user": "1319287761048723458"
    },
    {
        "central_user": "366785595",
        "adjacent_user": "1200433400508821509"
    },
    {
        "central_user": "366785595",
        "adjacent_user": "1510887055533830144"
    },
    {
        "central_user": "366785595",
        "adjacent_user": "73922604"
    },
    {
        "central_user": "366785595",
        "adjacent_user": "16310397"
    },
    {
        "central_user": "366785595",
        "adjacent_user": "1339488762"
    },
    {
        "central_user": "366785595",
        "adjacent_user": "3026990185"
    },
    {
        "central_user": "366785595",
        "adjacent_user": "1374317368361447434"
    },
    {
        "central_user": "366785595",
        "adjacent_user": "1355216628737339395"
    },
    {
        "central_user": "366785595",
        "adjacent_user": "4148621113"
    },
    {
        "central_user": "1567243553931251713",
        "adjacent_user": "1548977419"
    },
    {
        "central_user": "1567243553931251713",
        "adjacent_user": "2162812627"
    },
    {
        "central_user": "1567243553931251713",
        "adjacent_user": "44196397"
    },
    {
        "central_user": "1567243553931251713",
        "adjacent_user": "91416107"
    },
    {
        "central_user": "1064293020055547905",
        "adjacent_user": "1349149096909668363"
    },
    {
        "central_user": "1064293020055547905",
        "adjacent_user": "1108472017144201216"
    },
    {
        "central_user": "1064293020055547905",
        "adjacent_user": "1082197856"
    },
    {
        "central_user": "1064293020055547905",
        "adjacent_user": "18956073"
    },
    {
        "central_user": "1064293020055547905",
        "adjacent_user": "85726335"
    },
    {
        "central_user": "1064293020055547905",
        "adjacent_user": "939091"
    },
    {
        "central_user": "1064293020055547905",
        "adjacent_user": "1591834567207522305"
    },
    {
        "central_user": "1053997053175652352",
        "adjacent_user": "32804484"
    },
    {
        "central_user": "1053997053175652352",
        "adjacent_user": "58127051"
    },
    {
        "central_user": "1053997053175652352",
        "adjacent_user": "3315264553"
    },
    {
        "central_user": "1053997053175652352",
        "adjacent_user": "15012486"
    },
    {
        "central_user": "1226126755716632580",
        "adjacent_user": "85726335"
    },
    {
        "central_user": "1226126755716632580",
        "adjacent_user": "44196397"
    },
    {
        "central_user": "1226126755716632580",
        "adjacent_user": "1433543337068400641"
    },
    {
        "central_user": "1226126755716632580",
        "adjacent_user": "30354991"
    },
    {
        "central_user": "980850228684361728",
        "adjacent_user": "1686901686185721857"
    },
    {
        "central_user": "980850228684361728",
        "adjacent_user": "3315264553"
    },
    {
        "central_user": "980850228684361728",
        "adjacent_user": "1481780764609941508"
    },
    {
        "central_user": "980850228684361728",
        "adjacent_user": "537709549"
    },
    {
        "central_user": "980850228684361728",
        "adjacent_user": "46302096"
    },
    {
        "central_user": "1346349319138381824",
        "adjacent_user": "1222894323152195586"
    },
    {
        "central_user": "1346349319138381824",
        "adjacent_user": "89421672"
    },
    {
        "central_user": "1346349319138381824",
        "adjacent_user": "1510780961281409025"
    },
    {
        "central_user": "1346349319138381824",
        "adjacent_user": "1260881050005315586"
    },
    {
        "central_user": "19301471",
        "adjacent_user": "1594006318326730753"
    },
    {
        "central_user": "19301471",
        "adjacent_user": "803694179079458816"
    },
    {
        "central_user": "19301471",
        "adjacent_user": "811757810841255936"
    },
    {
        "central_user": "19301471",
        "adjacent_user": "1658544339574743044"
    },
    {
        "central_user": "19301471",
        "adjacent_user": "1226916043278442496"
    },
    {
        "central_user": "19301471",
        "adjacent_user": "1421125270099087360"
    },
    {
        "central_user": "19301471",
        "adjacent_user": "1586012373290205185"
    },
    {
        "central_user": "19301471",
        "adjacent_user": "1586889837386276864"
    },
    {
        "central_user": "19301471",
        "adjacent_user": "938478035484811264"
    },
    {
        "central_user": "858259578181500928",
        "adjacent_user": "1222773302441148416"
    },
    {
        "central_user": "858259578181500928",
        "adjacent_user": "1382209054999646212"
    },
    {
        "central_user": "858259578181500928",
        "adjacent_user": "815966620300480514"
    },
    {
        "central_user": "858259578181500928",
        "adjacent_user": "1619059471484948480"
    },
    {
        "central_user": "858259578181500928",
        "adjacent_user": "1686551250538528769"
    },
    {
        "central_user": "1685762052252368896",
        "adjacent_user": "811757810841255936"
    },
    {
        "central_user": "1685762052252368896",
        "adjacent_user": "1658544339574743044"
    },
    {
        "central_user": "1685762052252368896",
        "adjacent_user": "1226916043278442496"
    },
    {
        "central_user": "1685762052252368896",
        "adjacent_user": "1513958941536886787"
    },
    {
        "central_user": "1685762052252368896",
        "adjacent_user": "830465860825292800"
    },
    {
        "central_user": "1685762052252368896",
        "adjacent_user": "1393763457539977216"
    },
    {
        "central_user": "1685762052252368896",
        "adjacent_user": "1586889837386276864"
    },
    {
        "central_user": "1685762052252368896",
        "adjacent_user": "1676993370533634049"
    },
    {
        "central_user": "1161995768028418048",
        "adjacent_user": "15012486"
    },
    {
        "central_user": "1161995768028418048",
        "adjacent_user": "191871143"
    },
    {
        "central_user": "1161995768028418048",
        "adjacent_user": "39844876"
    },
    {
        "central_user": "1161995768028418048",
        "adjacent_user": "1319287761048723458"
    },
    {
        "central_user": "21222563",
        "adjacent_user": "3315264553"
    },
    {
        "central_user": "21222563",
        "adjacent_user": "1519657253799817218"
    },
    {
        "central_user": "21222563",
        "adjacent_user": "11134252"
    },
    {
        "central_user": "21222563",
        "adjacent_user": "1349149096909668363"
    },
    {
        "central_user": "3252965109",
        "adjacent_user": "840054480590651394"
    },
    {
        "central_user": "3252965109",
        "adjacent_user": "1241075086565634048"
    },
    {
        "central_user": "3252965109",
        "adjacent_user": "1212728697431572480"
    },
    {
        "central_user": "3252965109",
        "adjacent_user": "1029956092124516353"
    },
    {
        "central_user": "742736402102652929",
        "adjacent_user": "29097819"
    },
    {
        "central_user": "742736402102652929",
        "adjacent_user": "1349149096909668363"
    },
    {
        "central_user": "742736402102652929",
        "adjacent_user": "33608041"
    },
    {
        "central_user": "742736402102652929",
        "adjacent_user": "4018888580"
    },
    {
        "central_user": "264119038",
        "adjacent_user": "1490466596531355650"
    },
    {
        "central_user": "264119038",
        "adjacent_user": "3096147528"
    },
    {
        "central_user": "264119038",
        "adjacent_user": "46302096"
    },
    {
        "central_user": "264119038",
        "adjacent_user": "32804484"
    },
    {
        "central_user": "264119038",
        "adjacent_user": "890061634181373952"
    },
    {
        "central_user": "1335094216435716098",
        "adjacent_user": "44196397"
    },
    {
        "central_user": "1335094216435716098",
        "adjacent_user": "1115495508519182336"
    },
    {
        "central_user": "1335094216435716098",
        "adjacent_user": "17128248"
    },
    {
        "central_user": "1335094216435716098",
        "adjacent_user": "4429003533"
    },
    {
        "central_user": "1335094216435716098",
        "adjacent_user": "780460754910732288"
    },
    {
        "central_user": "1335094216435716098",
        "adjacent_user": "1537523833837584384"
    },
    {
        "central_user": "1335094216435716098",
        "adjacent_user": "294293982"
    },
    {
        "central_user": "1110641495617359872",
        "adjacent_user": "2162812627"
    },
    {
        "central_user": "1110641495617359872",
        "adjacent_user": "3096147528"
    },
    {
        "central_user": "1110641495617359872",
        "adjacent_user": "44196397"
    },
    {
        "central_user": "1110641495617359872",
        "adjacent_user": "91416107"
    },
    {
        "central_user": "1110641495617359872",
        "adjacent_user": "1318263321745907713"
    },
    {
        "central_user": "1110641495617359872",
        "adjacent_user": "32804484"
    },
    {
        "central_user": "1110641495617359872",
        "adjacent_user": "1326229737551912960"
    },
    {
        "central_user": "1110641495617359872",
        "adjacent_user": "39844876"
    },
    {
        "central_user": "1110641495617359872",
        "adjacent_user": "1221462414744596483"
    },
    {
        "central_user": "1110641495617359872",
        "adjacent_user": "1355721251180961792"
    },
    {
        "central_user": "1786243182881382400",
        "adjacent_user": "30354991"
    },
    {
        "central_user": "1786243182881382400",
        "adjacent_user": "3315264553"
    },
    {
        "central_user": "1786243182881382400",
        "adjacent_user": "132339474"
    },
    {
        "central_user": "1786243182881382400",
        "adjacent_user": "85726335"
    },
    {
        "central_user": "1786243182881382400",
        "adjacent_user": "14377605"
    },
    {
        "central_user": "1184965776505102336",
        "adjacent_user": "5709522"
    },
    {
        "central_user": "1184965776505102336",
        "adjacent_user": "790507178343866368"
    },
    {
        "central_user": "1184965776505102336",
        "adjacent_user": "44196397"
    },
    {
        "central_user": "1184965776505102336",
        "adjacent_user": "939091"
    },
    {
        "central_user": "1432014119931162629",
        "adjacent_user": "3315264553"
    },
    {
        "central_user": "1432014119931162629",
        "adjacent_user": "939091"
    },
    {
        "central_user": "1432014119931162629",
        "adjacent_user": "44196397"
    },
    {
        "central_user": "1432014119931162629",
        "adjacent_user": "1349149096909668363"
    },
    {
        "central_user": "1093555979361415168",
        "adjacent_user": "11134252"
    },
    {
        "central_user": "1093555979361415168",
        "adjacent_user": "1349149096909668363"
    },
    {
        "central_user": "1093555979361415168",
        "adjacent_user": "1221462414744596483"
    },
    {
        "central_user": "1093555979361415168",
        "adjacent_user": "1108472017144201216"
    },
    {
        "central_user": "1093555979361415168",
        "adjacent_user": "130003441"
    },
    {
        "central_user": "1093555979361415168",
        "adjacent_user": "1082197856"
    },
    {
        "central_user": "1325144798794182656",
        "adjacent_user": "11134252"
    },
    {
        "central_user": "1325144798794182656",
        "adjacent_user": "32804484"
    },
    {
        "central_user": "1325144798794182656",
        "adjacent_user": "1326229737551912960"
    },
    {
        "central_user": "1325144798794182656",
        "adjacent_user": "1108472017144201216"
    },
    {
        "central_user": "1325144798794182656",
        "adjacent_user": "3315264553"
    },
    {
        "central_user": "1325144798794182656",
        "adjacent_user": "1707763125280219136"
    },
    {
        "central_user": "738172438823849984",
        "adjacent_user": "240454812"
    },
    {
        "central_user": "738172438823849984",
        "adjacent_user": "17469289"
    },
    {
        "central_user": "738172438823849984",
        "adjacent_user": "1349149096909668363"
    },
    {
        "central_user": "738172438823849984",
        "adjacent_user": "1224185690713460736"
    },
    {
        "central_user": "738172438823849984",
        "adjacent_user": "1350150750966603777"
    },
    {
        "central_user": "738172438823849984",
        "adjacent_user": "1686901686185721857"
    },
    {
        "central_user": "738172438823849984",
        "adjacent_user": "1060573081935249409"
    },
    {
        "central_user": "738172438823849984",
        "adjacent_user": "1432014119931162629"
    },
    {
        "central_user": "738172438823849984",
        "adjacent_user": "14159148"
    },
    {
        "central_user": "738172438823849984",
        "adjacent_user": "1170411750841176064"
    },
    {
        "central_user": "738172438823849984",
        "adjacent_user": "55329156"
    },
    {
        "central_user": "738172438823849984",
        "adjacent_user": "130003441"
    },
    {
        "central_user": "738172438823849984",
        "adjacent_user": "1619059471484948480"
    },
    {
        "central_user": "738172438823849984",
        "adjacent_user": "44196397"
    },
    {
        "central_user": "4115436320",
        "adjacent_user": "1221462414744596483"
    },
    {
        "central_user": "4115436320",
        "adjacent_user": "85726335"
    },
    {
        "central_user": "4115436320",
        "adjacent_user": "1092382328"
    },
    {
        "central_user": "4115436320",
        "adjacent_user": "803694179079458816"
    },
    {
        "central_user": "4115436320",
        "adjacent_user": "30354991"
    },
    {
        "central_user": "4115436320",
        "adjacent_user": "1349149096909668363"
    },
    {
        "central_user": "4115436320",
        "adjacent_user": "14377605"
    },
    {
        "central_user": "4115436320",
        "adjacent_user": "813286"
    },
    {
        "central_user": "1216879828529483776",
        "adjacent_user": "14377605"
    },
    {
        "central_user": "1216879828529483776",
        "adjacent_user": "16523905"
    },
    {
        "central_user": "1216879828529483776",
        "adjacent_user": "3315264553"
    },
    {
        "central_user": "1216879828529483776",
        "adjacent_user": "374712154"
    },
    {
        "central_user": "1658544339574743044",
        "adjacent_user": "830465860825292800"
    },
    {
        "central_user": "1658544339574743044",
        "adjacent_user": "1393763457539977216"
    },
    {
        "central_user": "1658544339574743044",
        "adjacent_user": "1586889837386276864"
    },
    {
        "central_user": "1658544339574743044",
        "adjacent_user": "1676993370533634049"
    },
    {
        "central_user": "1658544339574743044",
        "adjacent_user": "811757810841255936"
    },
    {
        "central_user": "1658544339574743044",
        "adjacent_user": "1226916043278442496"
    },
    {
        "central_user": "1658544339574743044",
        "adjacent_user": "1513958941536886787"
    },
    {
        "central_user": "1524028258647425024",
        "adjacent_user": "939091"
    },
    {
        "central_user": "1524028258647425024",
        "adjacent_user": "30354991"
    },
    {
        "central_user": "1524028258647425024",
        "adjacent_user": "813286"
    },
    {
        "central_user": "1524028258647425024",
        "adjacent_user": "3315264553"
    },
    {
        "central_user": "17147215",
        "adjacent_user": "803694179079458816"
    },
    {
        "central_user": "17147215",
        "adjacent_user": "3315264553"
    },
    {
        "central_user": "17147215",
        "adjacent_user": "1323730225067339784"
    },
    {
        "central_user": "17147215",
        "adjacent_user": "742143"
    },
    {
        "central_user": "17147215",
        "adjacent_user": "1367531"
    },
    {
        "central_user": "17147215",
        "adjacent_user": "7587032"
    },
    {
        "central_user": "17147215",
        "adjacent_user": "939091"
    },
    {
        "central_user": "147722554",
        "adjacent_user": "1683440309768708096"
    },
    {
        "central_user": "147722554",
        "adjacent_user": "3044247194"
    },
    {
        "central_user": "147722554",
        "adjacent_user": "1255201907867439104"
    },
    {
        "central_user": "147722554",
        "adjacent_user": "1510780961281409025"
    },
    {
        "central_user": "815999326908346368",
        "adjacent_user": "44196397"
    },
    {
        "central_user": "815999326908346368",
        "adjacent_user": "890061634181373952"
    },
    {
        "central_user": "815999326908346368",
        "adjacent_user": "1355721251180961792"
    },
    {
        "central_user": "815999326908346368",
        "adjacent_user": "537709549"
    },
    {
        "central_user": "1274618051711778816",
        "adjacent_user": "2727885399"
    },
    {
        "central_user": "1274618051711778816",
        "adjacent_user": "1069599820912910337"
    },
    {
        "central_user": "1274618051711778816",
        "adjacent_user": "890061634181373952"
    },
    {
        "central_user": "1274618051711778816",
        "adjacent_user": "742143"
    },
    {
        "central_user": "1511383855764279300",
        "adjacent_user": "813286"
    },
    {
        "central_user": "1511383855764279300",
        "adjacent_user": "357606935"
    },
    {
        "central_user": "1511383855764279300",
        "adjacent_user": "85726335"
    },
    {
        "central_user": "1511383855764279300",
        "adjacent_user": "1433543337068400641"
    },
    {
        "central_user": "350370681",
        "adjacent_user": "11855772"
    },
    {
        "central_user": "350370681",
        "adjacent_user": "1682895247020371968"
    },
    {
        "central_user": "350370681",
        "adjacent_user": "54830654"
    },
    {
        "central_user": "350370681",
        "adjacent_user": "1604139215406727170"
    },
    {
        "central_user": "104248289",
        "adjacent_user": "3096147528"
    },
    {
        "central_user": "104248289",
        "adjacent_user": "44196397"
    },
    {
        "central_user": "104248289",
        "adjacent_user": "14377605"
    },
    {
        "central_user": "104248289",
        "adjacent_user": "1686901686185721857"
    },
    {
        "central_user": "1461271472966873088",
        "adjacent_user": "890061634181373952"
    },
    {
        "central_user": "1461271472966873088",
        "adjacent_user": "39344374"
    },
    {
        "central_user": "1461271472966873088",
        "adjacent_user": "44196397"
    },
    {
        "central_user": "1461271472966873088",
        "adjacent_user": "91416107"
    },
    {
        "central_user": "1461271472966873088",
        "adjacent_user": "263547117"
    },
    {
        "central_user": "1461271472966873088",
        "adjacent_user": "1686901686185721857"
    },
    {
        "central_user": "1442771175801692163",
        "adjacent_user": "2467791"
    },
    {
        "central_user": "1442771175801692163",
        "adjacent_user": "890061634181373952"
    },
    {
        "central_user": "1442771175801692163",
        "adjacent_user": "35773039"
    },
    {
        "central_user": "1442771175801692163",
        "adjacent_user": "130003441"
    },
    {
        "central_user": "1442771175801692163",
        "adjacent_user": "537709549"
    },
    {
        "central_user": "1442771175801692163",
        "adjacent_user": "939091"
    },
    {
        "central_user": "47408060",
        "adjacent_user": "3108351"
    },
    {
        "central_user": "47408060",
        "adjacent_user": "2467791"
    },
    {
        "central_user": "47408060",
        "adjacent_user": "14515799"
    },
    {
        "central_user": "47408060",
        "adjacent_user": "17839398"
    },
    {
        "central_user": "47408060",
        "adjacent_user": "564111558"
    },
    {
        "central_user": "1445425425061142529",
        "adjacent_user": "3108351"
    },
    {
        "central_user": "1445425425061142529",
        "adjacent_user": "17469289"
    },
    {
        "central_user": "1445425425061142529",
        "adjacent_user": "32804484"
    },
    {
        "central_user": "1445425425061142529",
        "adjacent_user": "1367531"
    },
    {
        "central_user": "1293219170956374016",
        "adjacent_user": "3566101392"
    },
    {
        "central_user": "1293219170956374016",
        "adjacent_user": "867369030092443648"
    },
    {
        "central_user": "1293219170956374016",
        "adjacent_user": "851815900256886786"
    },
    {
        "central_user": "1293219170956374016",
        "adjacent_user": "723504719843356673"
    },
    {
        "central_user": "830465860825292800",
        "adjacent_user": "1226916043278442496"
    },
    {
        "central_user": "830465860825292800",
        "adjacent_user": "1513958941536886787"
    },
    {
        "central_user": "830465860825292800",
        "adjacent_user": "1393763457539977216"
    },
    {
        "central_user": "830465860825292800",
        "adjacent_user": "19301471"
    },
    {
        "central_user": "830465860825292800",
        "adjacent_user": "1586889837386276864"
    },
    {
        "central_user": "830465860825292800",
        "adjacent_user": "1676993370533634049"
    },
    {
        "central_user": "830465860825292800",
        "adjacent_user": "811757810841255936"
    },
    {
        "central_user": "830465860825292800",
        "adjacent_user": "1658544339574743044"
    },
    {
        "central_user": "1627816040800321544",
        "adjacent_user": "44196397"
    },
    {
        "central_user": "1627816040800321544",
        "adjacent_user": "803694179079458816"
    },
    {
        "central_user": "1627816040800321544",
        "adjacent_user": "30354991"
    },
    {
        "central_user": "1627816040800321544",
        "adjacent_user": "3315264553"
    },
    {
        "central_user": "560817194",
        "adjacent_user": "28862779"
    },
    {
        "central_user": "560817194",
        "adjacent_user": "21651982"
    },
    {
        "central_user": "560817194",
        "adjacent_user": "4239551"
    },
    {
        "central_user": "560817194",
        "adjacent_user": "44196397"
    },
    {
        "central_user": "560817194",
        "adjacent_user": "629698642"
    },
    {
        "central_user": "560817194",
        "adjacent_user": "69156861"
    },
    {
        "central_user": "560817194",
        "adjacent_user": "1318263321745907713"
    },
    {
        "central_user": "560817194",
        "adjacent_user": "1663308107240570880"
    },
    {
        "central_user": "560817194",
        "adjacent_user": "191871143"
    },
    {
        "central_user": "560817194",
        "adjacent_user": "1686551250538528769"
    },
    {
        "central_user": "560817194",
        "adjacent_user": "1432014119931162629"
    },
    {
        "central_user": "560817194",
        "adjacent_user": "1319287761048723458"
    },
    {
        "central_user": "560817194",
        "adjacent_user": "50772918"
    },
    {
        "central_user": "1676993370533634049",
        "adjacent_user": "1658544339574743044"
    },
    {
        "central_user": "1676993370533634049",
        "adjacent_user": "1226916043278442496"
    },
    {
        "central_user": "1676993370533634049",
        "adjacent_user": "1513958941536886787"
    },
    {
        "central_user": "1676993370533634049",
        "adjacent_user": "830465860825292800"
    },
    {
        "central_user": "1676993370533634049",
        "adjacent_user": "1393763457539977216"
    },
    {
        "central_user": "1676993370533634049",
        "adjacent_user": "1586889837386276864"
    },
    {
        "central_user": "1676993370533634049",
        "adjacent_user": "811757810841255936"
    },
    {
        "central_user": "1547695908497764352",
        "adjacent_user": "85726335"
    },
    {
        "central_user": "1547695908497764352",
        "adjacent_user": "1349149096909668363"
    },
    {
        "central_user": "1547695908497764352",
        "adjacent_user": "818893114979061761"
    },
    {
        "central_user": "1547695908497764352",
        "adjacent_user": "3315264553"
    },
    {
        "central_user": "1476230581885321219",
        "adjacent_user": "939091"
    },
    {
        "central_user": "1476230581885321219",
        "adjacent_user": "191871143"
    },
    {
        "central_user": "1476230581885321219",
        "adjacent_user": "813286"
    },
    {
        "central_user": "1476230581885321219",
        "adjacent_user": "537709549"
    },
    {
        "central_user": "361891992",
        "adjacent_user": "1333171793201225728"
    },
    {
        "central_user": "361891992",
        "adjacent_user": "629698642"
    },
    {
        "central_user": "361891992",
        "adjacent_user": "1349149096909668363"
    },
    {
        "central_user": "361891992",
        "adjacent_user": "2442888666"
    },
    {
        "central_user": "1513958941536886787",
        "adjacent_user": "1676993370533634049"
    },
    {
        "central_user": "1513958941536886787",
        "adjacent_user": "811757810841255936"
    },
    {
        "central_user": "1513958941536886787",
        "adjacent_user": "1658544339574743044"
    },
    {
        "central_user": "1513958941536886787",
        "adjacent_user": "1226916043278442496"
    },
    {
        "central_user": "1513958941536886787",
        "adjacent_user": "830465860825292800"
    },
    {
        "central_user": "1513958941536886787",
        "adjacent_user": "390941487"
    },
    {
        "central_user": "1513958941536886787",
        "adjacent_user": "1685762052252368896"
    },
    {
        "central_user": "1513958941536886787",
        "adjacent_user": "1393763457539977216"
    },
    {
        "central_user": "1513958941536886787",
        "adjacent_user": "1586889837386276864"
    },
    {
        "central_user": "1689604836336033793",
        "adjacent_user": "1076925599074172928"
    },
    {
        "central_user": "1689604836336033793",
        "adjacent_user": "946698502171750401"
    },
    {
        "central_user": "1689604836336033793",
        "adjacent_user": "3026990185"
    },
    {
        "central_user": "1689604836336033793",
        "adjacent_user": "1339488762"
    },
    {
        "central_user": "1575353896926674945",
        "adjacent_user": "1686901686185721857"
    },
    {
        "central_user": "1575353896926674945",
        "adjacent_user": "3315264553"
    },
    {
        "central_user": "1575353896926674945",
        "adjacent_user": "55329156"
    },
    {
        "central_user": "1575353896926674945",
        "adjacent_user": "1367531"
    },
    {
        "central_user": "1339488762",
        "adjacent_user": "11134252"
    },
    {
        "central_user": "1339488762",
        "adjacent_user": "1349149096909668363"
    },
    {
        "central_user": "1339488762",
        "adjacent_user": "1510887055533830144"
    },
    {
        "central_user": "1339488762",
        "adjacent_user": "1619059471484948480"
    },
    {
        "central_user": "1339488762",
        "adjacent_user": "16310397"
    },
    {
        "central_user": "1339488762",
        "adjacent_user": "3005733012"
    },
    {
        "central_user": "1339488762",
        "adjacent_user": "3026990185"
    },
    {
        "central_user": "1339488762",
        "adjacent_user": "131546062"
    },
    {
        "central_user": "1339488762",
        "adjacent_user": "939091"
    },
    {
        "central_user": "1321357723729100800",
        "adjacent_user": "1593929531148144645"
    },
    {
        "central_user": "1321357723729100800",
        "adjacent_user": "939091"
    },
    {
        "central_user": "1321357723729100800",
        "adjacent_user": "30354991"
    },
    {
        "central_user": "1321357723729100800",
        "adjacent_user": "1349149096909668363"
    },
    {
        "central_user": "1006795705",
        "adjacent_user": "152415842"
    },
    {
        "central_user": "1006795705",
        "adjacent_user": "196324920"
    },
    {
        "central_user": "1006795705",
        "adjacent_user": "274669412"
    },
    {
        "central_user": "1006795705",
        "adjacent_user": "964363105663795203"
    },
    {
        "central_user": "933089797295316992",
        "adjacent_user": "14159148"
    },
    {
        "central_user": "933089797295316992",
        "adjacent_user": "811229675758505984"
    },
    {
        "central_user": "933089797295316992",
        "adjacent_user": "196324920"
    },
    {
        "central_user": "933089797295316992",
        "adjacent_user": "9624742"
    },
    {
        "central_user": "933089797295316992",
        "adjacent_user": "1350150750966603777"
    },
    {
        "central_user": "32189808",
        "adjacent_user": "1429400366819512323"
    },
    {
        "central_user": "32189808",
        "adjacent_user": "1401592047035895812"
    },
    {
        "central_user": "32189808",
        "adjacent_user": "1133510366422392833"
    },
    {
        "central_user": "32189808",
        "adjacent_user": "1374317368361447434"
    },
    {
        "central_user": "32189808",
        "adjacent_user": "116579971"
    },
    {
        "central_user": "811757810841255936",
        "adjacent_user": "1658544339574743044"
    },
    {
        "central_user": "811757810841255936",
        "adjacent_user": "1226916043278442496"
    },
    {
        "central_user": "811757810841255936",
        "adjacent_user": "1513958941536886787"
    },
    {
        "central_user": "811757810841255936",
        "adjacent_user": "830465860825292800"
    },
    {
        "central_user": "811757810841255936",
        "adjacent_user": "1421125270099087360"
    },
    {
        "central_user": "811757810841255936",
        "adjacent_user": "1586012373290205185"
    },
    {
        "central_user": "811757810841255936",
        "adjacent_user": "1393763457539977216"
    },
    {
        "central_user": "811757810841255936",
        "adjacent_user": "19301471"
    },
    {
        "central_user": "811757810841255936",
        "adjacent_user": "1586889837386276864"
    },
    {
        "central_user": "811757810841255936",
        "adjacent_user": "938478035484811264"
    },
    {
        "central_user": "811757810841255936",
        "adjacent_user": "1676993370533634049"
    },
    {
        "central_user": "811757810841255936",
        "adjacent_user": "1594006318326730753"
    },
    {
        "central_user": "811757810841255936",
        "adjacent_user": "803694179079458816"
    },
    {
        "central_user": "1030893594410926081",
        "adjacent_user": "3096147528"
    },
    {
        "central_user": "1030893594410926081",
        "adjacent_user": "2734574376"
    },
    {
        "central_user": "1030893594410926081",
        "adjacent_user": "611986351"
    },
    {
        "central_user": "1030893594410926081",
        "adjacent_user": "2853461537"
    },
    {
        "central_user": "1030893594410926081",
        "adjacent_user": "130003441"
    },
    {
        "central_user": "1320279147143376902",
        "adjacent_user": "1241075086565634048"
    },
    {
        "central_user": "1320279147143376902",
        "adjacent_user": "29097819"
    },
    {
        "central_user": "1320279147143376902",
        "adjacent_user": "1320142328795987968"
    },
    {
        "central_user": "1320279147143376902",
        "adjacent_user": "1069599820912910337"
    },
    {
        "central_user": "1587223428557262848",
        "adjacent_user": "803694179079458816"
    },
    {
        "central_user": "1587223428557262848",
        "adjacent_user": "30354991"
    },
    {
        "central_user": "1587223428557262848",
        "adjacent_user": "1349149096909668363"
    },
    {
        "central_user": "1587223428557262848",
        "adjacent_user": "3315264553"
    },
    {
        "central_user": "1587223428557262848",
        "adjacent_user": "1367531"
    },
    {
        "central_user": "1587223428557262848",
        "adjacent_user": "1323730225067339784"
    },
    {
        "central_user": "1587223428557262848",
        "adjacent_user": "939091"
    },
    {
        "central_user": "1241075086565634048",
        "adjacent_user": "1212728697431572480"
    },
    {
        "central_user": "1241075086565634048",
        "adjacent_user": "893642836062633984"
    },
    {
        "central_user": "1241075086565634048",
        "adjacent_user": "1317473581476052993"
    },
    {
        "central_user": "1241075086565634048",
        "adjacent_user": "1320142328795987968"
    },
    {
        "central_user": "1167577715530010624",
        "adjacent_user": "537709549"
    },
    {
        "central_user": "1167577715530010624",
        "adjacent_user": "46302096"
    },
    {
        "central_user": "1167577715530010624",
        "adjacent_user": "11134252"
    },
    {
        "central_user": "1167577715530010624",
        "adjacent_user": "1355721251180961792"
    },
    {
        "central_user": "1167577715530010624",
        "adjacent_user": "9300262"
    },
    {
        "central_user": "1393763457539977216",
        "adjacent_user": "1586889837386276864"
    },
    {
        "central_user": "1393763457539977216",
        "adjacent_user": "1676993370533634049"
    },
    {
        "central_user": "1393763457539977216",
        "adjacent_user": "811757810841255936"
    },
    {
        "central_user": "1393763457539977216",
        "adjacent_user": "1658544339574743044"
    },
    {
        "central_user": "1393763457539977216",
        "adjacent_user": "1226916043278442496"
    },
    {
        "central_user": "1393763457539977216",
        "adjacent_user": "1513958941536886787"
    },
    {
        "central_user": "1393763457539977216",
        "adjacent_user": "830465860825292800"
    },
    {
        "central_user": "1546400347312525312",
        "adjacent_user": "50769180"
    },
    {
        "central_user": "1546400347312525312",
        "adjacent_user": "1367531"
    },
    {
        "central_user": "1546400347312525312",
        "adjacent_user": "761597234530152450"
    },
    {
        "central_user": "1546400347312525312",
        "adjacent_user": "240454812"
    },
    {
        "central_user": "1086976130819809280",
        "adjacent_user": "55329156"
    },
    {
        "central_user": "1086976130819809280",
        "adjacent_user": "39344374"
    },
    {
        "central_user": "1086976130819809280",
        "adjacent_user": "131546062"
    },
    {
        "central_user": "1086976130819809280",
        "adjacent_user": "11134252"
    },
    {
        "central_user": "1086976130819809280",
        "adjacent_user": "939091"
    },
    {
        "central_user": "1086976130819809280",
        "adjacent_user": "1349149096909668363"
    },
    {
        "central_user": "1086976130819809280",
        "adjacent_user": "1108472017144201216"
    },
    {
        "central_user": "806827006444720128",
        "adjacent_user": "1593355784519401472"
    },
    {
        "central_user": "806827006444720128",
        "adjacent_user": "1287258532027478016"
    },
    {
        "central_user": "806827006444720128",
        "adjacent_user": "190541883"
    },
    {
        "central_user": "806827006444720128",
        "adjacent_user": "3026990185"
    },
    {
        "central_user": "806827006444720128",
        "adjacent_user": "1683440309768708096"
    },
    {
        "central_user": "417508380",
        "adjacent_user": "85726335"
    },
    {
        "central_user": "417508380",
        "adjacent_user": "14377605"
    },
    {
        "central_user": "417508380",
        "adjacent_user": "30354991"
    },
    {
        "central_user": "417508380",
        "adjacent_user": "1367531"
    },
    {
        "central_user": "1402816876850253827",
        "adjacent_user": "1235110990347268096"
    },
    {
        "central_user": "1402816876850253827",
        "adjacent_user": "1544939293319188480"
    },
    {
        "central_user": "1402816876850253827",
        "adjacent_user": "1735221284219310080"
    },
    {
        "central_user": "1402816876850253827",
        "adjacent_user": "1569434143540531200"
    },
    {
        "central_user": "1590949724558876672",
        "adjacent_user": "17469289"
    },
    {
        "central_user": "1590949724558876672",
        "adjacent_user": "803694179079458816"
    },
    {
        "central_user": "1590949724558876672",
        "adjacent_user": "130003441"
    },
    {
        "central_user": "1590949724558876672",
        "adjacent_user": "1319287761048723458"
    },
    {
        "central_user": "1643092408886804489",
        "adjacent_user": "44196397"
    },
    {
        "central_user": "1643092408886804489",
        "adjacent_user": "69156861"
    },
    {
        "central_user": "1643092408886804489",
        "adjacent_user": "29097819"
    },
    {
        "central_user": "1643092408886804489",
        "adjacent_user": "191871143"
    },
    {
        "central_user": "1643092408886804489",
        "adjacent_user": "39844876"
    },
    {
        "central_user": "1643092408886804489",
        "adjacent_user": "1319287761048723458"
    },
    {
        "central_user": "1793830475837890560",
        "adjacent_user": "85726335"
    },
    {
        "central_user": "1793830475837890560",
        "adjacent_user": "30354991"
    },
    {
        "central_user": "1793830475837890560",
        "adjacent_user": "1355721251180961792"
    },
    {
        "central_user": "1793830475837890560",
        "adjacent_user": "1323730225067339784"
    },
    {
        "central_user": "1629931728298024967",
        "adjacent_user": "1326229737551912960"
    },
    {
        "central_user": "1629931728298024967",
        "adjacent_user": "463142998"
    },
    {
        "central_user": "1629931728298024967",
        "adjacent_user": "890061634181373952"
    },
    {
        "central_user": "1629931728298024967",
        "adjacent_user": "3096147528"
    },
    {
        "central_user": "1764145049263276032",
        "adjacent_user": "1222773302441148416"
    },
    {
        "central_user": "1764145049263276032",
        "adjacent_user": "1117210361592205312"
    },
    {
        "central_user": "1764145049263276032",
        "adjacent_user": "89421672"
    },
    {
        "central_user": "1764145049263276032",
        "adjacent_user": "91416107"
    },
    {
        "central_user": "127547640",
        "adjacent_user": "246357149"
    },
    {
        "central_user": "127547640",
        "adjacent_user": "1349149096909668363"
    },
    {
        "central_user": "127547640",
        "adjacent_user": "3315264553"
    },
    {
        "central_user": "127547640",
        "adjacent_user": "1593635660681957399"
    },
    {
        "central_user": "127547640",
        "adjacent_user": "1519657253799817218"
    },
    {
        "central_user": "127547640",
        "adjacent_user": "939091"
    },
    {
        "central_user": "946698502171750401",
        "adjacent_user": "1445341550230212612"
    },
    {
        "central_user": "946698502171750401",
        "adjacent_user": "49035671"
    },
    {
        "central_user": "946698502171750401",
        "adjacent_user": "49616273"
    },
    {
        "central_user": "946698502171750401",
        "adjacent_user": "1510887055533830144"
    },
    {
        "central_user": "946698502171750401",
        "adjacent_user": "1619059471484948480"
    },
    {
        "central_user": "946698502171750401",
        "adjacent_user": "73922604"
    },
    {
        "central_user": "946698502171750401",
        "adjacent_user": "1339488762"
    },
    {
        "central_user": "946698502171750401",
        "adjacent_user": "1329376427976880135"
    },
    {
        "central_user": "1741968261468790784",
        "adjacent_user": "30354991"
    },
    {
        "central_user": "1741968261468790784",
        "adjacent_user": "374712154"
    },
    {
        "central_user": "1741968261468790784",
        "adjacent_user": "85726335"
    },
    {
        "central_user": "1741968261468790784",
        "adjacent_user": "44196397"
    },
    {
        "central_user": "47851175",
        "adjacent_user": "11134252"
    },
    {
        "central_user": "47851175",
        "adjacent_user": "1349149096909668363"
    },
    {
        "central_user": "47851175",
        "adjacent_user": "1350150750966603777"
    },
    {
        "central_user": "47851175",
        "adjacent_user": "1319287761048723458"
    },
    {
        "central_user": "47851175",
        "adjacent_user": "1313128625680592896"
    },
    {
        "central_user": "1503760973726896132",
        "adjacent_user": "803694179079458816"
    },
    {
        "central_user": "1503760973726896132",
        "adjacent_user": "32804484"
    },
    {
        "central_user": "1503760973726896132",
        "adjacent_user": "30354991"
    },
    {
        "central_user": "1503760973726896132",
        "adjacent_user": "85726335"
    },
    {
        "central_user": "2318676117",
        "adjacent_user": "876926961741742081"
    },
    {
        "central_user": "2318676117",
        "adjacent_user": "202963011"
    },
    {
        "central_user": "2318676117",
        "adjacent_user": "3563066357"
    },
    {
        "central_user": "2318676117",
        "adjacent_user": "118838969"
    },
    {
        "central_user": "2318676117",
        "adjacent_user": "196324920"
    },
    {
        "central_user": "2318676117",
        "adjacent_user": "14169130"
    },
    {
        "central_user": "2318676117",
        "adjacent_user": "78761555"
    },
    {
        "central_user": "800415833868513281",
        "adjacent_user": "3315264553"
    },
    {
        "central_user": "800415833868513281",
        "adjacent_user": "44196397"
    },
    {
        "central_user": "800415833868513281",
        "adjacent_user": "803694179079458816"
    },
    {
        "central_user": "800415833868513281",
        "adjacent_user": "30354991"
    },
    {
        "central_user": "1594940499739103232",
        "adjacent_user": "1619059471484948480"
    },
    {
        "central_user": "1594940499739103232",
        "adjacent_user": "44196397"
    },
    {
        "central_user": "1594940499739103232",
        "adjacent_user": "1349149096909668363"
    },
    {
        "central_user": "1594940499739103232",
        "adjacent_user": "1323730225067339784"
    },
    {
        "central_user": "1637636270762459136",
        "adjacent_user": "16523905"
    },
    {
        "central_user": "1637636270762459136",
        "adjacent_user": "1355721251180961792"
    },
    {
        "central_user": "1637636270762459136",
        "adjacent_user": "1319287761048723458"
    },
    {
        "central_user": "1637636270762459136",
        "adjacent_user": "375721095"
    },
    {
        "central_user": "1637636270762459136",
        "adjacent_user": "132339474"
    },
    {
        "central_user": "1354840375806967812",
        "adjacent_user": "44196397"
    },
    {
        "central_user": "1354840375806967812",
        "adjacent_user": "939091"
    },
    {
        "central_user": "1354840375806967812",
        "adjacent_user": "803694179079458816"
    },
    {
        "central_user": "1354840375806967812",
        "adjacent_user": "30354991"
    },
    {
        "central_user": "1354840375806967812",
        "adjacent_user": "1349149096909668363"
    },
    {
        "central_user": "1060647489945133056",
        "adjacent_user": "1465405597"
    },
    {
        "central_user": "1060647489945133056",
        "adjacent_user": "2467791"
    },
    {
        "central_user": "1060647489945133056",
        "adjacent_user": "815966620300480514"
    },
    {
        "central_user": "1060647489945133056",
        "adjacent_user": "1619059471484948480"
    },
    {
        "central_user": "25610446",
        "adjacent_user": "939091"
    },
    {
        "central_user": "25610446",
        "adjacent_user": "131546062"
    },
    {
        "central_user": "25610446",
        "adjacent_user": "11134252"
    },
    {
        "central_user": "25610446",
        "adjacent_user": "1349149096909668363"
    },
    {
        "central_user": "25610446",
        "adjacent_user": "1082197856"
    },
    {
        "central_user": "1380683172615086080",
        "adjacent_user": "1339488762"
    },
    {
        "central_user": "1380683172615086080",
        "adjacent_user": "18626979"
    },
    {
        "central_user": "1380683172615086080",
        "adjacent_user": "55650719"
    },
    {
        "central_user": "1380683172615086080",
        "adjacent_user": "2211735352"
    },
    {
        "central_user": "1362436222098968579",
        "adjacent_user": "1075435039008219136"
    },
    {
        "central_user": "1362436222098968579",
        "adjacent_user": "1006795705"
    },
    {
        "central_user": "1362436222098968579",
        "adjacent_user": "274669412"
    },
    {
        "central_user": "1362436222098968579",
        "adjacent_user": "1060647489945133056"
    },
    {
        "central_user": "1362436222098968579",
        "adjacent_user": "1291344470575910914"
    },
    {
        "central_user": "240454812",
        "adjacent_user": "11134252"
    },
    {
        "central_user": "240454812",
        "adjacent_user": "939091"
    },
    {
        "central_user": "240454812",
        "adjacent_user": "30354991"
    },
    {
        "central_user": "240454812",
        "adjacent_user": "813286"
    },
    {
        "central_user": "3297135136",
        "adjacent_user": "30354991"
    },
    {
        "central_user": "3297135136",
        "adjacent_user": "33608041"
    },
    {
        "central_user": "3297135136",
        "adjacent_user": "116579971"
    },
    {
        "central_user": "3297135136",
        "adjacent_user": "1490466596531355650"
    },
    {
        "central_user": "3297135136",
        "adjacent_user": "21651982"
    },
    {
        "central_user": "3297135136",
        "adjacent_user": "3096147528"
    },
    {
        "central_user": "60518094",
        "adjacent_user": "2161051908"
    },
    {
        "central_user": "60518094",
        "adjacent_user": "848279118"
    },
    {
        "central_user": "60518094",
        "adjacent_user": "611986351"
    },
    {
        "central_user": "60518094",
        "adjacent_user": "801203059359678464"
    },
    {
        "central_user": "60518094",
        "adjacent_user": "1222773302441148416"
    },
    {
        "central_user": "964363105663795203",
        "adjacent_user": "2211735352"
    },
    {
        "central_user": "964363105663795203",
        "adjacent_user": "64047409"
    },
    {
        "central_user": "964363105663795203",
        "adjacent_user": "85726335"
    },
    {
        "central_user": "964363105663795203",
        "adjacent_user": "18626979"
    },
    {
        "central_user": "1586012373290205185",
        "adjacent_user": "44196397"
    },
    {
        "central_user": "1586012373290205185",
        "adjacent_user": "19301471"
    },
    {
        "central_user": "1586012373290205185",
        "adjacent_user": "1586889837386276864"
    },
    {
        "central_user": "1586012373290205185",
        "adjacent_user": "938478035484811264"
    },
    {
        "central_user": "1586012373290205185",
        "adjacent_user": "1594006318326730753"
    },
    {
        "central_user": "1586012373290205185",
        "adjacent_user": "803694179079458816"
    },
    {
        "central_user": "1586012373290205185",
        "adjacent_user": "811757810841255936"
    },
    {
        "central_user": "1586012373290205185",
        "adjacent_user": "1658544339574743044"
    },
    {
        "central_user": "1586012373290205185",
        "adjacent_user": "1226916043278442496"
    },
    {
        "central_user": "1586012373290205185",
        "adjacent_user": "1421125270099087360"
    },
    {
        "central_user": "1465405597",
        "adjacent_user": "1060647489945133056"
    },
    {
        "central_user": "1465405597",
        "adjacent_user": "64047409"
    },
    {
        "central_user": "1465405597",
        "adjacent_user": "815966620300480514"
    },
    {
        "central_user": "1465405597",
        "adjacent_user": "152415842"
    },
    {
        "central_user": "1465405597",
        "adjacent_user": "1619059471484948480"
    },
    {
        "central_user": "1465405597",
        "adjacent_user": "267695291"
    },
    {
        "central_user": "59103986",
        "adjacent_user": "130003441"
    },
    {
        "central_user": "59103986",
        "adjacent_user": "1241075086565634048"
    },
    {
        "central_user": "59103986",
        "adjacent_user": "537709549"
    },
    {
        "central_user": "59103986",
        "adjacent_user": "1389236563117228038"
    },
    {
        "central_user": "59103986",
        "adjacent_user": "44196397"
    },
    {
        "central_user": "59103986",
        "adjacent_user": "1029956092124516353"
    },
    {
        "central_user": "1574690362626494466",
        "adjacent_user": "1164622276563615744"
    },
    {
        "central_user": "1574690362626494466",
        "adjacent_user": "1339488762"
    },
    {
        "central_user": "1574690362626494466",
        "adjacent_user": "1646865286744735748"
    },
    {
        "central_user": "1574690362626494466",
        "adjacent_user": "1374317368361447434"
    },
    {
        "central_user": "65159946",
        "adjacent_user": "1323730225067339784"
    },
    {
        "central_user": "65159946",
        "adjacent_user": "939091"
    },
    {
        "central_user": "65159946",
        "adjacent_user": "931286316"
    },
    {
        "central_user": "65159946",
        "adjacent_user": "44196397"
    },
    {
        "central_user": "1321555504980779011",
        "adjacent_user": "44196397"
    },
    {
        "central_user": "1321555504980779011",
        "adjacent_user": "1318263321745907713"
    },
    {
        "central_user": "1321555504980779011",
        "adjacent_user": "1432014119931162629"
    },
    {
        "central_user": "1321555504980779011",
        "adjacent_user": "1355721251180961792"
    },
    {
        "central_user": "1750296850081722368",
        "adjacent_user": "1429400366819512323"
    },
    {
        "central_user": "1750296850081722368",
        "adjacent_user": "939091"
    },
    {
        "central_user": "1750296850081722368",
        "adjacent_user": "32804484"
    },
    {
        "central_user": "1750296850081722368",
        "adjacent_user": "1221462414744596483"
    },
    {
        "central_user": "1421125270099087360",
        "adjacent_user": "1586012373290205185"
    },
    {
        "central_user": "1421125270099087360",
        "adjacent_user": "19301471"
    },
    {
        "central_user": "1421125270099087360",
        "adjacent_user": "1586889837386276864"
    },
    {
        "central_user": "1421125270099087360",
        "adjacent_user": "938478035484811264"
    },
    {
        "central_user": "1421125270099087360",
        "adjacent_user": "1594006318326730753"
    },
    {
        "central_user": "1421125270099087360",
        "adjacent_user": "803694179079458816"
    },
    {
        "central_user": "1421125270099087360",
        "adjacent_user": "811757810841255936"
    },
    {
        "central_user": "1421125270099087360",
        "adjacent_user": "1658544339574743044"
    },
    {
        "central_user": "1421125270099087360",
        "adjacent_user": "1226916043278442496"
    },
    {
        "central_user": "1575420448384221184",
        "adjacent_user": "1164622276563615744"
    },
    {
        "central_user": "1575420448384221184",
        "adjacent_user": "49035671"
    },
    {
        "central_user": "1575420448384221184",
        "adjacent_user": "1510887055533830144"
    },
    {
        "central_user": "1575420448384221184",
        "adjacent_user": "946698502171750401"
    },
    {
        "central_user": "1761218053646483456",
        "adjacent_user": "1313128625680592896"
    },
    {
        "central_user": "1761218053646483456",
        "adjacent_user": "89421672"
    },
    {
        "central_user": "1761218053646483456",
        "adjacent_user": "735811158469423105"
    },
    {
        "central_user": "1761218053646483456",
        "adjacent_user": "1646865286744735748"
    },
    {
        "central_user": "1761218053646483456",
        "adjacent_user": "1349149096909668363"
    },
    {
        "central_user": "1761218053646483456",
        "adjacent_user": "9624742"
    },
    {
        "central_user": "1805826141455794176",
        "adjacent_user": "780460754910732288"
    },
    {
        "central_user": "1805826141455794176",
        "adjacent_user": "3096147528"
    },
    {
        "central_user": "1805826141455794176",
        "adjacent_user": "46302096"
    },
    {
        "central_user": "1805826141455794176",
        "adjacent_user": "1622588070246641666"
    },
    {
        "central_user": "851804318688841728",
        "adjacent_user": "851815900256886786"
    },
    {
        "central_user": "851804318688841728",
        "adjacent_user": "1803485639255736320"
    },
    {
        "central_user": "851804318688841728",
        "adjacent_user": "1293219170956374016"
    },
    {
        "central_user": "851804318688841728",
        "adjacent_user": "3566101392"
    },
    {
        "central_user": "178978113",
        "adjacent_user": "1333171793201225728"
    },
    {
        "central_user": "178978113",
        "adjacent_user": "1967216306"
    },
    {
        "central_user": "178978113",
        "adjacent_user": "1349149096909668363"
    },
    {
        "central_user": "178978113",
        "adjacent_user": "9624742"
    },
    {
        "central_user": "178978113",
        "adjacent_user": "1350150750966603777"
    },
    {
        "central_user": "178978113",
        "adjacent_user": "14499829"
    },
    {
        "central_user": "890569045191278592",
        "adjacent_user": "104611567"
    },
    {
        "central_user": "890569045191278592",
        "adjacent_user": "974147064002064384"
    },
    {
        "central_user": "890569045191278592",
        "adjacent_user": "1274618051711778816"
    },
    {
        "central_user": "890569045191278592",
        "adjacent_user": "1211816467844354049"
    },
    {
        "central_user": "890569045191278592",
        "adjacent_user": "1212728697431572480"
    },
    {
        "central_user": "3566101392",
        "adjacent_user": "851815900256886786"
    },
    {
        "central_user": "3566101392",
        "adjacent_user": "851804318688841728"
    },
    {
        "central_user": "3566101392",
        "adjacent_user": "723504719843356673"
    },
    {
        "central_user": "3566101392",
        "adjacent_user": "1293219170956374016"
    },
    {
        "central_user": "851815900256886786",
        "adjacent_user": "851804318688841728"
    },
    {
        "central_user": "851815900256886786",
        "adjacent_user": "723504719843356673"
    },
    {
        "central_user": "851815900256886786",
        "adjacent_user": "1293219170956374016"
    },
    {
        "central_user": "851815900256886786",
        "adjacent_user": "3566101392"
    },
    {
        "central_user": "1801166133481160704",
        "adjacent_user": "1794622121014136832"
    },
    {
        "central_user": "1801166133481160704",
        "adjacent_user": "1814529457702772736"
    },
    {
        "central_user": "1801166133481160704",
        "adjacent_user": "1793811290617724928"
    },
    {
        "central_user": "1801166133481160704",
        "adjacent_user": "187739965"
    }
]